aestate/__init__.py
aestate/conf.py
aestate/ajson/__init__.py
aestate/ajson/ajson.py
aestate/base/__init__.py
aestate/base/anno.py
aestate/base/manage.py
aestate/base/model.py
aestate/base/proxy.py
aestate/dbs/__init__.py
aestate/dbs/base.py
aestate/dbs/_mssql/__init__.py
aestate/dbs/_mysql/__init__.py
aestate/dbs/_mysql/tag.py
aestate/exception/__init__.py
aestate/i18n/__init__.py
aestate/util/CompulsoryRun.py
aestate/util/Log.py
aestate/util/__init__.py
aestate/util/others.py
aestate/util/sqlOpera.py
aestate/work/Adapter.py
aestate/work/Annotation.py
aestate/work/AopContainer.py
aestate/work/Cache.py
aestate/work/Config.py
aestate/work/Manage.py
aestate/work/Modes.py
aestate/work/Serialize.py
aestate/work/__init__.py
aestate/work/orm.py
aestate/work/repository.py
aestate/work/commands/__init__.py
aestate/work/proxy/SqlOperaProxy.py
aestate/work/proxy/__init__.py
aestate/work/sql/ExecuteSql.py
aestate/work/sql/ProxyOpera.py
aestate/work/sql/__init__.py
aestate/work/xmlhandler/XMLScriptBuilder.py
aestate/work/xmlhandler/__init__.py
aestate/work/xmlhandler/base.py
aestate/work/xmlhandler/final.py
aestate/work/xmlhandler/nodes.py
aestate/work/xmlhandler/utils.py
Aestate-1.1.0.dist-info/LICENSE
Aestate-1.1.0.dist-info/METADATA
Aestate-1.1.0.dist-info/WHEEL
Aestate-1.1.0.dist-info/entry_points.txt
Aestate-1.1.0.dist-info/top_level.txt
Aestate-1.1.0.dist-info/RECORD
