Metadata-Version: 2.1
Name: Aestate
Version: 1.1.0
Summary: Aestate framework for Python,You can see:https://gitee.com/aecode/aestate
Home-page: https://gitee.com/aecode/aestate
Author: CACode
Author-email: cacode@163.com
License: Apache License 2.0
Project-URL: Bug Tracker, https://gitee.com/aecode/aestate/issues
Platform: UNKNOWN
Classifier: Programming Language :: Python :: 3
Classifier: License :: OSI Approved :: MIT License
Classifier: Operating System :: OS Independent
Classifier: Topic :: Database
Requires-Python: >=3.7
License-File: LICENSE
Requires-Dist: prettytable
Requires-Dist: cryptography
Requires-Dist: psutil
Requires-Dist: DBUtils
Requires-Dist: simplejson
